kinliuren/__init__.py
kinliuren/kinliuren.py
kinliuren-0.1.2.9.dist-info/METADATA
kinliuren-0.1.2.9.dist-info/WHEEL
kinliuren-0.1.2.9.dist-info/top_level.txt
kinliuren-0.1.2.9.dist-info/RECORD
