Metadata-Version: 2.1
Name: kinliuren
Version: 0.1.2.9
Summary: Dailiuren (大六壬) is one of the three greatest Chinese Divination systems ever.
Home-page: https://github.com/kentang2017/kinliuren
Author: Ken Tang
Author-email: kinyeah@gmail.com
Classifier: Programming Language :: Python :: 3
Classifier: License :: OSI Approved :: MIT License
Classifier: Operating System :: OS Independent
